Metadata-Version: 2.1
Name: vtk-module
Version: 0.0.1
Summary: fixes the vtk problems
Home-page: UNKNOWN
License: UNKNOWN
Platform: UNKNOWN
